smartonetoonefield/__init__.py
smartonetoonefield/apps.py
smartonetoonefield/fields.py
django_smartonetoonefield-0.1.2.dist-info/METADATA
django_smartonetoonefield-0.1.2.dist-info/WHEEL
django_smartonetoonefield-0.1.2.dist-info/RECORD
