Metadata-Version: 2.3
Name: django-smartonetoonefield
Version: 0.1.2
Summary: Django app to make one-to-one relations easier to work with
License: BSD
Author: blag
Author-email: blag@users.noreply.github.com
Requires-Python: >=3.10
Classifier: Development Status :: 5 - Production/Stable
Classifier: Environment :: Web Environment
Classifier: Framework :: Django
Classifier: Framework :: Django :: 4.2
Classifier: Framework :: Django :: 5.0
Classifier: Framework :: Django :: 5.1
Classifier: Framework :: Django :: 5.2
Classifier: Intended Audience :: Developers
Classifier: License :: OSI Approved :: BSD License
Classifier: Operating System :: OS Independent
Classifier: Programming Language :: Python
Classifier: Programming Language :: Python :: 3.10
Classifier: Programming Language :: Python :: 3.11
Classifier: Programming Language :: Python :: 3.12
Requires-Dist: django (>=4.2)
Project-URL: Documentation, https://www.fusionbox.com/blog/detail/django-onetoonefields-are-hard-to-use-lets-make-them-better/551/
Project-URL: Issues, https://github.com/blag/django-smartonetoonefield/issues
Project-URL: Repository, https://github.com/blag/django-smartonetoonefield
